dawdreamer-0.8.3.dist-info/RECORD
dawdreamer-0.8.3.dist-info/LICENSE
dawdreamer-0.8.3.dist-info/WHEEL
dawdreamer-0.8.3.dist-info/top_level.txt
dawdreamer-0.8.3.dist-info/METADATA
dawdreamer/__init__.py
dawdreamer/dawdreamer.so
dawdreamer/licenses/JUCE_7_LICENSE
dawdreamer/licenses/PYBIND_11_LICENSE
dawdreamer/licenses/JUCE_5_LICENSE
dawdreamer/licenses/FAUST_LICENSE
dawdreamer/licenses/LIBSAMPLERATE_LICENSE
dawdreamer/licenses/RUBBERBAND_LICENSE
dawdreamer/faust/__init__.py
dawdreamer/faust/box/__init__.py
dawdreamer/faust/signal/__init__.py
dawdreamer/architecture/alsa-console.cpp
dawdreamer/architecture/minimal-effect.c
dawdreamer/architecture/faustui.js
dawdreamer/architecture/plot.cpp
dawdreamer/architecture/lv2.cpp
dawdreamer/architecture/au-instrument.cpp
dawdreamer/architecture/lv2ui.cpp
dawdreamer/architecture/netjack-console.cpp
dawdreamer/architecture/puredata.cpp
dawdreamer/architecture/jack-ros.cpp
dawdreamer/architecture/octave.cpp
dawdreamer/architecture/pure.c
dawdreamer/architecture/csvplot.cpp
dawdreamer/architecture/mathdoctexts-default.txt
dawdreamer/architecture/oscio-qt.cpp
dawdreamer/architecture/minimal.cpp
dawdreamer/architecture/ios-coreaudio-jack.cpp
dawdreamer/architecture/bela.cpp
dawdreamer/architecture/jack.rs
dawdreamer/architecture/module.cpp
dawdreamer/architecture/c-jack-gtk.c
dawdreamer/architecture/minimal.c
dawdreamer/architecture/dssi.cpp
dawdreamer/architecture/minimal.d
dawdreamer/architecture/dummy-mem.cpp
dawdreamer/architecture/latexheader.tex
dawdreamer/architecture/sndfile.cpp
dawdreamer/architecture/minimal-fixed-point.cpp
dawdreamer/architecture/mathdoctexts-de.txt
dawdreamer/architecture/netjack-qt.cpp
dawdreamer/architecture/jack-qt.cpp
dawdreamer/architecture/dplug.d
dawdreamer/architecture/supercollider.cpp
dawdreamer/architecture/ladspa.cpp
dawdreamer/architecture/mathdoctexts-it.txt
dawdreamer/architecture/lv2qtgui.h
dawdreamer/architecture/ca-qt.cpp
dawdreamer/architecture/oscio-gtk.cpp
dawdreamer/architecture/scheduler.cpp
dawdreamer/architecture/mathdoctexts-en.txt
dawdreamer/architecture/matlabplot.cpp
