Metadata-Version: 2.1
Name: dawdreamer
Version: 0.8.3
Summary: An audio-processing Python library supporting core DAW features
Home-page: https://github.com/DBraun/DawDreamer
Author: David Braun
Author-email: braun@ccrma.stanford.edu
Project-URL: Documentation, https://dirt.design/DawDreamer
Project-URL: Source, https://github.com/DBraun/DawDreamer
Keywords: audio music sound
Classifier: Development Status :: 3 - Alpha
Classifier: Intended Audience :: Developers
Classifier: License :: OSI Approved :: GNU General Public License v3 (GPLv3)
Classifier: Operating System :: MacOS
Classifier: Operating System :: Microsoft :: Windows
Classifier: Operating System :: POSIX :: Linux
Classifier: Programming Language :: C++
Classifier: Programming Language :: Python
Classifier: Topic :: Multimedia :: Sound/Audio
Classifier: Programming Language :: Python :: 3.8
Classifier: Programming Language :: Python :: 3.9
Classifier: Programming Language :: Python :: 3.10
Classifier: Programming Language :: Python :: 3.11
Classifier: Programming Language :: Python :: 3.12
Requires-Python: >=3.8
License-File: LICENSE
